llama_index/py.typed
llama_index/vector_stores/singlestoredb/__init__.py
llama_index/vector_stores/singlestoredb/base.py
llama_index_vector_stores_singlestoredb-0.4.2.dist-info/METADATA
llama_index_vector_stores_singlestoredb-0.4.2.dist-info/WHEEL
llama_index_vector_stores_singlestoredb-0.4.2.dist-info/licenses/LICENSE
llama_index_vector_stores_singlestoredb-0.4.2.dist-info/RECORD
