Metadata-Version: 2.4
Name: llama-index-vector-stores-singlestoredb
Version: 0.4.2
Summary: llama-index vector_stores singlestoredb integration
Author-email: Your Name <you@example.com>
License-Expression: MIT
License-File: LICENSE
Requires-Python: <4.0,>=3.9
Requires-Dist: llama-index-core<0.15,>=0.13.0
Requires-Dist: singlestoredb<0.11,>=0.10.5
